mlflow_logger_ext/__init__.py
mlflow_logger_ext/base.py
mlflow_logger_ext/external/__init__.py
mlflow_logger_ext/external/mmlab.py
mlflow_logger_ext/mlflow_wrapper.py
mlflow_logger_ext/tests/__init__.py
mlflow_logger_ext/tests/test_mlflow.py
mlflow_logger_ext/tracker.py
mlflow_logger_ext/utils.py
mlflow_logger_ext-0.2.2.dist-info/LICENSE
mlflow_logger_ext-0.2.2.dist-info/WHEEL
mlflow_logger_ext-0.2.2.dist-info/METADATA
mlflow_logger_ext-0.2.2.dist-info/RECORD
